radMLBench/__init__.py
radMLBench/metadata.yaml
radMLBench/radMLBench.py
radMLBench-1.1.dist-info/LICENSE.txt
radMLBench-1.1.dist-info/METADATA
radMLBench-1.1.dist-info/WHEEL
radMLBench-1.1.dist-info/top_level.txt
radMLBench-1.1.dist-info/zip-safe
radMLBench-1.1.dist-info/RECORD
