Metadata-Version: 2.1
Name: radMLBench
Version: 1.1
Summary: A Python wrapper for the radMLBench data repository.
Home-page: https://github.com/aydindemircioglu/radMLBench
Author: Aydin Demircioglu
Author-email: aydin.demircioglu@uk-essen.de
License: MIT
Keywords: radiomics,data mining,benchmark,machine learning,data analysis,data sets,data science,wrapper
Classifier: Intended Audience :: Science/Research
Classifier: License :: OSI Approved :: MIT License
Classifier: Programming Language :: Python :: 3.7
Requires-Python: >=3.6.0
License-File: LICENSE.txt
Requires-Dist: pandas (>=1.2.0)
Requires-Dist: requests (>=2.18.0)
Requires-Dist: pyyaml (>=5.2)
Requires-Dist: joblib (>=0.12.0)
Requires-Dist: numpy (>=1.18.0)
Requires-Dist: scikit-learn (>=0.20.0)
